<?xml version="1.0" encoding="utf-8" ?>
<dwsync>
<file name="logo.png" server="ftp.kombest.de" local="128907812751749375" remote="128907747000000000" />
<file name="background - Kopie.png" server="ftp.kombest.de" local="128905261372149384" remote="128907743400000000" />
<file name="background.png" server="ftp.kombest.de" local="128907812262439375" remote="128907743400000000" />
<file name="bg.gif" server="ftp.kombest.de" local="128881718737930000" remote="128907746400000000" />
<file name="bg_btm.gif" server="ftp.kombest.de" local="128881718737970000" remote="128907746400000000" />
<file name="bg_top.gif" server="ftp.kombest.de" local="128881718737950000" remote="128907746400000000" />
<file name="btn_contact_large.jpg" server="ftp.kombest.de" local="128904688453060000" remote="128907746400000000" />
<file name="btn_contact_large.png" server="ftp.kombest.de" local="128905254670389384" remote="128907746400000000" />
<file name="button.png" server="ftp.kombest.de" local="128883366283070000" remote="128907746400000000" />
<file name="collapsed.gif" server="ftp.kombest.de" local="128886584214491388" remote="128907746400000000" />
<file name="expanded.gif" server="ftp.kombest.de" local="128886584214661388" remote="128907746400000000" />
<file name="f_bg.png" server="ftp.kombest.de" local="128905750265733375" remote="128907747000000000" />
<file name="haken.gif" server="ftp.kombest.de" local="128885380853145368" remote="128907747000000000" />
<file name="icon-credit.png" server="ftp.kombest.de" local="128887945428743301" remote="128907747000000000" />
<file name="logo.gif" server="ftp.kombest.de" local="128905767220673375" remote="128907747000000000" />
<file name="mast.gif" server="ftp.kombest.de" local="128881718737850000" remote="128907747000000000" />
<file name="pageBg.gif" server="ftp.kombest.de" local="128881718737880000" remote="128907747600000000" />
<file name="skype-bkg.png" server="ftp.kombest.de" local="128881943955160000" remote="128907748200000000" />
<file name="skype-button.png" server="ftp.kombest.de" local="128881943090660000" remote="128907748200000000" />
<file name="tab_l_of.gif" server="ftp.kombest.de" local="128881718737900000" remote="128907748200000000" />
<file name="tab_l_on.gif" server="ftp.kombest.de" local="128881718737760000" remote="128907748200000000" />
<file name="tab_s_of.gif" server="ftp.kombest.de" local="128881718737710000" remote="128907748200000000" />
<file name="tab_s_on.gif" server="ftp.kombest.de" local="128881718737830000" remote="128907748200000000" />
<file name="topBg.gif" server="ftp.kombest.de" local="128881718737690000" remote="128907748200000000" />
<file name="topL.gif" server="ftp.kombest.de" local="128905765607393375" remote="128907748200000000" />
<file name="topR.gif" server="ftp.kombest.de" local="128881718737810000" remote="128907748200000000" />
<file name="www.png" server="ftp.kombest.de" local="128906549547780000" remote="128907748800000000" />
<file name="favicon.ico" server="ftp.kombest.de" local="128907740438369375" remote="128907747000000000" />
<file name="icon-green.png" server="ftp.kombest.de" local="128907799232249375" remote="128907747000000000" />
<file name="icons.jpg" server="ftp.kombest.de" local="128909499320334000" remote="128909451000000000" />
<file name="senden.png" server="ftp.kombest.de" local="128909888420893393" remote="128909830800000000" />
</dwsync>